pyvsystems/__init__.py
pyvsystems/account.py
pyvsystems/chain.py
pyvsystems/contract.py
pyvsystems/contract_helper.py
pyvsystems/crypto.py
pyvsystems/deser.py
pyvsystems/error.py
pyvsystems/setting.py
pyvsystems/words.py
pyvsystems/wrapper.py
pyvsystems-0.4.0.dist-info/LICENSE
pyvsystems-0.4.0.dist-info/METADATA
pyvsystems-0.4.0.dist-info/WHEEL
pyvsystems-0.4.0.dist-info/top_level.txt
pyvsystems-0.4.0.dist-info/RECORD
