Metadata-Version: 2.1
Name: pyvsystems
Version: 0.4.0
Summary: A python wrapper for vsys api.
Home-page: https://github.com/virtualeconomy/pyvsystems
Author: V SYSTEMS
Author-email: developers@v.systems
License: MIT
Keywords: api wrapper,blockchain,vsystems,smart contract,supernode,defi
Requires-Python: >=3.6
License-File: LICENSE
Requires-Dist: requests
Requires-Dist: python-axolotl-curve25519
Requires-Dist: base58
